fastapi_response_time/__init__.py
fastapi_response_time/middleware.py
fastapi_response_time-0.1.0.dist-info/METADATA
fastapi_response_time-0.1.0.dist-info/WHEEL
fastapi_response_time-0.1.0.dist-info/top_level.txt
fastapi_response_time-0.1.0.dist-info/RECORD
